{
  "users": {
    "_comment_unifield": "The unifield user is a legacy user for Pakistan UF, we cannot easily change the username anymore",
    "per-host": {
      "benuc001": {
        "enable": [
          "uf_mz_maputo"
        ]
      },
      "benuc004": {
        "enable_roles": [
          "mast"
        ]
      },
      "benuc006": {
        "enable": [
          "unifield"
        ]
      },
      "benuc007": {
        "enable": [
          "yusuph",
          "uf_mz_beira"
        ]
      },
      "benuc009": {
        "enable_roles": [
          "mast"
        ]
      },
      "benuc010": {
        "enable": [
          "nicolas"
        ]
      },
      "benuc014": {
        "enable": [
          "uf_ht_port_a_piment"
        ],
        "enable_roles": [
          "mast"
        ]
      },
      "benuc015": {
        "enable": [
          "uf_cd_masisi"
        ],
        "enable_roles": [
          "mast"
        ]
      },
      "benuc016": {
        "enable_roles": [
          "mast"
        ]
      },
      "benuc018": {
        "enable": [
          "uf_ua_zyhtomyr"
        ]
      },
      "benuc020": {
        "enable": [
          "uf_pk_karashi",
          "unifield"
        ]
      },
      "benuc021": {
        "enable": [
          "unifield"
        ]
      },
      "benuc023": {
        "enable_roles": [
          "mast"
        ]
      },
      "benuc024": {
        "enable": [
          "uf_gn_kouroussa"
        ],
        "enable_roles": [
          "mast"
        ]
      },
      "benuc025": {
        "enable": [
          "uf_sl_baama"
        ],
        "enable_roles": [
          "mast"
        ]
      },
      "benuc026": {
        "enable": [
          "uf_sl_kenema"
        ],
        "enable_roles": [
          "mast"
        ]
      },
      "benuc027": {
        "enable_roles": [
          "mast"
        ]
      },
      "benuc030": {
        "enable": [
          "uf_cd_puc"
        ]
      },
      "benuc035": {
        "enable_roles": [
          "mast"
        ]
      },
      "benuc037": {
        "enable": [
          "uf_ke_embu"
        ],
        "enable_roles": [
          "mast"
        ]
      },
      "bevm001": {
        "enable": [
          "uf_cd_goma"
        ]
      },
      "bevm002": {
        "enable": [
          "tnl_bd_coxcoord",
          "uf_bd_coxcoord"
        ]
      },
      "bevm003": {
        "enable": [
          "uf_cd_kinshasacoord"
        ]
      },
      "bevm004": {
        "enable": [
          "uf_sl_freetown"
        ]
      },
      "bevm005": {
        "enable": [
          "uf_eg_maadi_annex1"
        ]
      },
      "bevm006": {
        "enable": [
          "uf_eg_maadi_coordination"
        ]
      },
      "bevm007": {
        "enable": [
          "uf_bi_bujumbura"
        ]
      },
      "bevm008": {
        "enable": [
          "uf_gn_conakry"
        ]
      },
      "bevm009": {
        "enable": [
          "uf_gn_sida"
        ]
      },
      "bevm010": {
        "enable": [
          "uf_cf_coordination"
        ]
      },
      "bevm011": {
        "enable": [
          "uf_cd_kinshasa_sida"
        ]
      },
      "bevm012": {
        "enable": [
          "uf_cf_castor_bangui"
        ]
      },
      "bevm013": {
        "enable": [
          "uf_ve_anzoategui"
        ]
      },
      "bevm014": {
        "enable": [
          "uf_ve_bolivar"
        ]
      },
      "bevm015": {
        "enable": [
          "uf_cm_bamenda"
        ]
      },
      "bevm016": {
        "enable": [
          "uf_ic_abidjan"
        ]
      },
      "bevm017": {
        "enable": [
          "uf_ke_kiambu"
        ]
      },
      "chk-emr-a": {
        "enable": [
          "gauthier"
        ]
      },
      "dhis2-dev": {
        "enable": [
          "yusuph"
        ]
      },
      "dhis2-hq-remote": {
        "enable": [
          "yusuph"
        ]
      },
      "dhis2-metadata": {
        "enable": [
          "yusuph"
        ]
      },
      "dhis2-prod": {
        "enable": [
          "yusuph"
        ]
      },
      "dhis2-validation": {
        "enable": [
          "didier",
          "yusuph"
        ]
      },
      "docker-dmz-1": {
        "enable": [
          "ian"
        ]
      },
      "mumbai-emr-a": {
        "enable": [
          "uf_in_mumbai"
        ]
      }
    },
    "remote_tunnel": [
      "damien",
      "didier",
      "dirk",
      "godfried",
      "joana",
      "kathy",
      "marco",
      "nicolas",
      "tnl_bd_coxcoord",
      "uf_bd_coxcoord",
      "uf_bi_bujumbura",
      "uf_cd_goma",
      "uf_cd_kinshasa_sida",
      "uf_cd_kinshasacoord",
      "uf_cd_masisi",
      "uf_cd_puc",
      "uf_cf_castor_bangui",
      "uf_cf_coordination",
      "uf_cm_bamenda",
      "uf_eg_maadi_annex1",
      "uf_eg_maadi_coordination",
      "uf_gn_conakry",
      "uf_gn_kouroussa",
      "uf_gn_sida",
      "uf_ht_port_a_piment",
      "uf_ic_abidjan",
      "uf_in_mumbai",
      "uf_ke_embu",
      "uf_ke_kiambu",
      "uf_mz_beira",
      "uf_mz_maputo",
      "uf_pk_karashi",
      "uf_sl_baama",
      "uf_sl_freetown",
      "uf_sl_kenema",
      "uf_ua_zyhtomyr",
      "uf_ve_anzoategui",
      "uf_ve_bolivar",
      "unifield",
      "vini"
    ],
    "roles": {
      "mast": [
        "damien",
        "didier",
        "godfried",
        "joana",
        "kathy",
        "vini",
        "yusuph"
      ]
    }
  }
}
